reahl/sqlalchemysupport/__init__.py
reahl/sqlalchemysupport/elixirmigration.py
reahl/sqlalchemysupport/migrations.py
reahl/sqlalchemysupport/sqlalchemysupport.py
reahl/sqlalchemysupport_dev/__init__.py
reahl/sqlalchemysupport_dev/fixtures.py
reahl/sqlalchemysupport_dev/test_sqlalchemysupport.py
reahl_sqlalchemysupport-7.0.3.dist-info/LICENSE
reahl_sqlalchemysupport-7.0.3.dist-info/METADATA
reahl_sqlalchemysupport-7.0.3.dist-info/WHEEL
reahl_sqlalchemysupport-7.0.3.dist-info/reahl-component.toml
reahl_sqlalchemysupport-7.0.3.dist-info/top_level.txt
reahl_sqlalchemysupport-7.0.3.dist-info/RECORD
