Metadata-Version: 2.1
Name: reahl-sqlalchemysupport
Version: 7.0.3
Summary: Support for using SqlAlchemy with Reahl.
Author-email: Iwan Vosloo <iwan@reahl.org>, Craig Sparks <craig@reahl.org>
Classifier: Development Status :: 5 - Production/Stable
Classifier: Intended Audience :: Developers
Classifier: License :: OSI Approved
Classifier: Operating System :: OS Independent
Classifier: Programming Language :: Python :: 3
Requires-Python: >=3.8
License-File: LICENSE
Requires-Dist: reahl-component <7.1,>=7.0
Requires-Dist: SQLAlchemy <2.1.999,>=1.4
Requires-Dist: alembic <1.13.999,>=0.9.6
Provides-Extra: test
Requires-Dist: pytest >=3.0 ; extra == 'test'
Requires-Dist: reahl-tofu ; extra == 'test'
Requires-Dist: reahl-stubble ; extra == 'test'
Requires-Dist: reahl-dev ; extra == 'test'
Requires-Dist: reahl-domain ; extra == 'test'
Requires-Dist: reahl-sqlitesupport ; extra == 'test'
Requires-Dist: wheel ; extra == 'test'
Requires-Dist: build ; extra == 'test'
